{
  "$schema": "https://json-schema.org/draft/2020-12/schema",
  "$id": "https://liberprimus-gpu.local/schemas/cuda/candidate-batch-abi-record-v0.schema.json",
  "title": "candidate-batch-abi-record-v0",
  "type": "object",
  "additionalProperties": true,
  "required": [
    "record_type",
    "stage_id",
    "abi_id",
    "abi_version",
    "abi_scope",
    "supported_surfaces",
    "cuda_execution_performed",
    "cuda_source_modified",
    "new_cuda_kernel_added",
    "gpu_benchmark_performed",
    "unsolved_page_cuda_used",
    "generated_body_publication_allowed",
    "generated_outputs_committed",
    "no_solve_claim",
    "solve_claim",
    "no_gpu_ci_safe"
  ],
  "properties": {
    "record_type": {"const": "candidate_batch_abi_record"},
    "stage_id": {"const": "stage-5u"},
    "abi_id": {"const": "candidate_batch_abi_v0"},
    "abi_version": {"const": 0},
    "abi_scope": {"const": "contract_only_no_execution"},
    "supported_surfaces": {"type": "array", "items": {"type": "string"}},
    "cuda_execution_performed": {"const": false},
    "cuda_source_modified": {"const": false},
    "new_cuda_kernel_added": {"const": false},
    "new_cuda_kernels_added": {"const": 0},
    "device_kernel_arithmetic_modified": {"const": false},
    "gpu_benchmark_performed": {"const": false},
    "performance_claim": {"const": false},
    "speedup_claim": {"const": false},
    "unsolved_page_cuda_used": {"const": false},
    "unsolved_page_cuda_allowed": {"const": false},
    "real_liber_primus_cuda_data_used": {"const": false},
    "canonical_corpus_active": {"const": false},
    "page_boundaries_final": {"const": false},
    "generated_body_publication_allowed": {"const": false},
    "generated_outputs_committed": {"const": false},
    "raw_data_processed": {"const": false},
    "codex_output_committed": {"const": false},
    "method_status_upgraded": {"const": false},
    "no_solve_claim": {"const": true},
    "solve_claim": {"const": false},
    "no_gpu_ci_safe": {"const": true}
  }
}
